tcfetch-0.5.1.dist-info/METADATA
tcfetch-0.5.1.dist-info/WHEEL
tcfetch.libs/libgcc_s-b5472b99.so.1
tcfetch/__init__.py
tcfetch/__init__.pyi
tcfetch/py.typed
tcfetch/tcfetch.pypy39-pp73-x86-linux-gnu.so
tcfetch-0.5.1.dist-info/RECORD
