Metadata-Version: 2.4
Name: tcfetch
Version: 0.5.1
Classifier: Programming Language :: Rust
Classifier: Programming Language :: Python :: Implementation :: CPython
Classifier: Programming Language :: Python :: Implementation :: PyPy
Summary: Download log files from Taskcluster CI systems
Author: James Graham <james@hoppipolla.co.uk>
Author-email: James Graham <james@hoppipolla.co.uk>
License: BSD-3-Clause
Requires-Python: >=3.7
